grim/__init__.py
grim/grim.py
grim/imputation/__init__.py
grim/imputation/setup.py
grim/imputation/graph_generation/__init__.py
grim/imputation/graph_generation/generate_neo4j_multi_hpf.py
grim/imputation/graph_generation/generate_neo4j_single_hpf.py
grim/imputation/graph_generation/nemo_to_hpf_csv.py
grim/imputation/graph_generation/wmda_download.py
grim/imputation/graph_generation/wmda_to_hpf_csv.py
grim/validation/__init__.py
grim/validation/parallel-imputation.py
grim/validation/reduce_loci.py
grim/validation/runfile.py
grim/validation/runfile_mp.py
grim/validation/runfile_mt.py
py_graph_imputation-0.0.6.dist-info/LICENSE
py_graph_imputation-0.0.6.dist-info/METADATA
py_graph_imputation-0.0.6.dist-info/WHEEL
py_graph_imputation-0.0.6.dist-info/top_level.txt
py_graph_imputation-0.0.6.dist-info/RECORD
